<annotation>
	<folder>images(r2d2)</folder>
	<filename>img156.jpg</filename>
	<path>/home/qcurteman/Desktop/images(r2d2)/img156.jpg</path>
	<source>
		<database>Unknown</database>
	</source>
	<size>
		<width>290</width>
		<height>450</height>
		<depth>3</depth>
	</size>
	<segmented>0</segmented>
	<object>
		<name>r2d2</name>
		<pose>Unspecified</pose>
		<truncated>0</truncated>
		<difficult>0</difficult>
		<bndbox>
			<xmin>6</xmin>
			<ymin>16</ymin>
			<xmax>284</xmax>
			<ymax>441</ymax>
		</bndbox>
	</object>
</annotation>
